tests/__init__.py
tests/sometests.py
wwa_app_example/__init__.py
wwa_app_example/main.py
wwa_app_example/test.py
wwa_app_test-1.0.1508506802.dist-info/METADATA
wwa_app_test-1.0.1508506802.dist-info/WHEEL
wwa_app_test-1.0.1508506802.dist-info/entry_points.txt
wwa_app_test-1.0.1508506802.dist-info/top_level.txt
wwa_app_test-1.0.1508506802.dist-info/RECORD
